[
  {
    "source": "EPA ECHO (Synthetic Representative)",
    "facility_name": "DuPont Washington Works Plant",
    "state": "WV",
    "city": "Parkersburg",
    "latitude": 39.28,
    "longitude": -81.53,
    "sic_code": "2869",
    "compliance_status": "Active",
    "data_source": "Synthetic - Representative PFAS Facilities",
    "fetch_date": "2026-03-28T21:49:14.918516",
    "note": "Representative facility based on known PFAS contamination areas"
  },
  {
    "source": "EPA ECHO (Synthetic Representative)",
    "facility_name": "Chemours Fayetteville Works",
    "state": "NC",
    "city": "Fayetteville",
    "latitude": 34.89,
    "longitude": -79.02,
    "sic_code": "2869",
    "compliance_status": "Active",
    "data_source": "Synthetic - Representative PFAS Facilities",
    "fetch_date": "2026-03-28T21:49:14.918524",
    "note": "Representative facility based on known PFAS contamination areas"
  },
  {
    "source": "EPA ECHO (Synthetic Representative)",
    "facility_name": "Chemours Corpus Christi Plant",
    "state": "TX",
    "city": "Corpus Christi",
    "latitude": 27.88,
    "longitude": -97.35,
    "sic_code": "2869",
    "compliance_status": "Active",
    "data_source": "Synthetic - Representative PFAS Facilities",
    "fetch_date": "2026-03-28T21:49:14.918524",
    "note": "Representative facility based on known PFAS contamination areas"
  },
  {
    "source": "EPA ECHO (Synthetic Representative)",
    "facility_name": "3M Company St. Paul Plant",
    "state": "MN",
    "city": "St. Paul",
    "latitude": 44.94,
    "longitude": -93.16,
    "sic_code": "2869",
    "compliance_status": "Active",
    "data_source": "Synthetic - Representative PFAS Facilities",
    "fetch_date": "2026-03-28T21:49:14.918527",
    "note": "Representative facility based on known PFAS contamination areas"
  },
  {
    "source": "EPA ECHO (Synthetic Representative)",
    "facility_name": "Wolverine Fire Training Site",
    "state": "MI",
    "city": "Oscoda",
    "latitude": 44.56,
    "longitude": -83.89,
    "sic_code": "8748",
    "compliance_status": "Active",
    "data_source": "Synthetic - Representative PFAS Facilities",
    "fetch_date": "2026-03-28T21:49:14.918528",
    "note": "Representative facility based on known PFAS contamination areas"
  },
  {
    "source": "EPA ECHO (Synthetic Representative)",
    "facility_name": "Pease Air Force Base",
    "state": "NH",
    "city": "Portsmouth",
    "latitude": 43.01,
    "longitude": -71.01,
    "sic_code": "9711",
    "compliance_status": "Active",
    "data_source": "Synthetic - Representative PFAS Facilities",
    "fetch_date": "2026-03-28T21:49:14.918529",
    "note": "Representative facility based on known PFAS contamination areas"
  },
  {
    "source": "EPA ECHO (Synthetic Representative)",
    "facility_name": "Military Ocean Terminal Earle",
    "state": "NJ",
    "city": "Colts Neck",
    "latitude": 40.44,
    "longitude": -74.05,
    "sic_code": "9999",
    "compliance_status": "Active",
    "data_source": "Synthetic - Representative PFAS Facilities",
    "fetch_date": "2026-03-28T21:49:14.918529",
    "note": "Representative facility based on known PFAS contamination areas"
  },
  {
    "source": "EPA ECHO (Synthetic Representative)",
    "facility_name": "Semprini Chemical Manufacturing",
    "state": "PA",
    "city": "Harrisburg",
    "latitude": 40.24,
    "longitude": -76.88,
    "sic_code": "2869",
    "compliance_status": "Active",
    "data_source": "Synthetic - Representative PFAS Facilities",
    "fetch_date": "2026-03-28T21:49:14.918530",
    "note": "Representative facility based on known PFAS contamination areas"
  },
  {
    "source": "EPA ECHO (Synthetic Representative)",
    "facility_name": "Fire Training Area - Wainwright",
    "state": "AK",
    "city": "Wainwright",
    "latitude": 61.63,
    "longitude": -145.06,
    "sic_code": "8748",
    "compliance_status": "Active",
    "data_source": "Synthetic - Representative PFAS Facilities",
    "fetch_date": "2026-03-28T21:49:14.918531",
    "note": "Representative facility based on known PFAS contamination areas"
  },
  {
    "source": "EPA ECHO (Synthetic Representative)",
    "facility_name": "AFB Fire Training Area",
    "state": "MI",
    "city": "Hurlburt Field",
    "latitude": 42.73,
    "longitude": -84.56,
    "sic_code": "8748",
    "compliance_status": "Active",
    "data_source": "Synthetic - Representative PFAS Facilities",
    "fetch_date": "2026-03-28T21:49:14.918531",
    "note": "Representative facility based on known PFAS contamination areas"
  }
]